req_project/__init__.py
req_project/commands/check_project.py
req_project/commands/delete_project.py
req_project/commands/generate_documentation.py
req_project/commands/git_for_project.py
req_project/commands/init_project.py
req_project/commands/map_project.py
req_project/commands/project_version.py
req_project/commands/pull.py
req_project/commands/push.py
req_project/commands/testing.py
req_project/commands/user.py
req_project/commands/version.py
req_project/commands/workspace_path.py
req_project/req_project.py
req_project/tools/configuration.py
req_project/tools/generate_uid.py
req_project/tools/git_bug.py
req_project/tools/logging.py
req_project/tools/map_reqifcapella.py
req_project/tools/passwords.py
req_project/tools/utility.py
req_project/tools/vs_code.py
req_project-0.1.3.dist-info/entry_points.txt
req_project-0.1.3.dist-info/WHEEL
req_project-0.1.3.dist-info/METADATA
req_project-0.1.3.dist-info/RECORD
