Metadata-Version: 2.1
Name: req-project
Version: 0.1.3
Summary: 
Author: Michael Naderhirn
Author-email: m.naderhirn@nmrobotic.com
Requires-Python: >=3.8,<4.0
Classifier: Programming Language :: Python :: 3
Classifier: Programming Language :: Python :: 3.10
Classifier: Programming Language :: Python :: 3.8
Classifier: Programming Language :: Python :: 3.9
Requires-Dist: GitPython (>=3.1.26,<4.0.0)
Requires-Dist: MarkupSafe (>=2.0.1,<3.0.0)
Requires-Dist: Pillow (>=9.0.0,<10.0.0)
Requires-Dist: lxml (>=4.7.1,<5.0.0)
Requires-Dist: openpyxl (>=3.0.9,<4.0.0)
Requires-Dist: pandas (>=1.4.0,<2.0.0)
Requires-Dist: passlib (>=1.7.4,<2.0.0)
Requires-Dist: pexpect (>=4.8.0,<5.0.0)
Requires-Dist: platformdirs (>=2.4.1,<3.0.0)
Requires-Dist: requests (>=2.27.1,<3.0.0)
Requires-Dist: strictdoc (>=0.0.18,<0.0.19)
Requires-Dist: svgwrite (>=1.4.1,<2.0.0)
Requires-Dist: textX (>=2.3.0,<3.0.0)
Requires-Dist: toml (>=0.10.2,<0.11.0)
Requires-Dist: winapps (>=0.2.0,<0.3.0)
